bellos_installer/__init__.py
bellos_installer/bellos_installer.py
bellos_installer-0.1.5.dist-info/LICENSE
bellos_installer-0.1.5.dist-info/METADATA
bellos_installer-0.1.5.dist-info/WHEEL
bellos_installer-0.1.5.dist-info/entry_points.txt
bellos_installer-0.1.5.dist-info/top_level.txt
bellos_installer-0.1.5.dist-info/RECORD
