Metadata-Version: 2.1
Name: bellos_installer
Version: 0.1.5
Summary: Install Bellos Scripting Languages into your Operating System
Author: RonaldsonBellande
Author-email: ronaldsonbellande@gmail.com
Project-URL: Home, https://github.com/Architecture-Mechanism/bellos_installer
Project-URL: Homepage, https://github.com/Architecture-Mechanism/bellos_installer
Project-URL: documentation, https://github.com/Architecture-Mechanism/bellos_installer
Project-URL: repository, https://github.com/Architecture-Mechanism/bellos_installer
Project-URL: Bug Reports, https://github.com/Architecture-Mechanism/bellos_installer/issues
Project-URL: Source, https://github.com/Architecture-Mechanism/bellos_installer
Keywords: bellos installer scripting languages
Classifier: Development Status :: 3 - Alpha
Classifier: Intended Audience :: Developers
Classifier: License :: OSI Approved :: GNU General Public License v3 (GPLv3)
Classifier: Programming Language :: Python :: 3
Classifier: Programming Language :: Python :: 3.6
Classifier: Programming Language :: Python :: 3.7
Classifier: Programming Language :: Python :: 3.8
Classifier: Programming Language :: Python :: 3.9
Requires-Python: >=3.0
License-File: LICENSE
Requires-Dist: requests
Requires-Dist: packaging
Provides-Extra: dev
Requires-Dist: pytest; extra == "dev"
Requires-Dist: pytest-cov[all]; extra == "dev"
Requires-Dist: mypy; extra == "dev"
Requires-Dist: black; extra == "dev"
